ecg/__init__.py
ecg/main.py
ecg/data/example.jpg
ecg-0.0.1.dist-info/LICENSE
ecg-0.0.1.dist-info/METADATA
ecg-0.0.1.dist-info/WHEEL
ecg-0.0.1.dist-info/entry_points.txt
ecg-0.0.1.dist-info/top_level.txt
ecg-0.0.1.dist-info/RECORD
